pathlib_/__init__.py
pathlib_/__main__.py
pathlib_/_base.py
pathlib_/_local.py
pathlib_/fnmatch_.py
pathlib_/glob_.py
pathlib_/posix.py
pathlib_/windows.py
pathlib_alt-0.1.2.dist-info/licenses/LICENSE
pathlib_alt-0.1.2.dist-info/METADATA
pathlib_alt-0.1.2.dist-info/WHEEL
pathlib_alt-0.1.2.dist-info/top_level.txt
pathlib_alt-0.1.2.dist-info/RECORD
